azure_graph_helper/__init__.py
azure_graph_helper/config.py
azure_graph_helper/graph_auth.py
azure_graph_helper/graph_utils.py
azure_graph_helper-1.0.1.2.dist-info/LICENSE
azure_graph_helper-1.0.1.2.dist-info/METADATA
azure_graph_helper-1.0.1.2.dist-info/WHEEL
azure_graph_helper-1.0.1.2.dist-info/top_level.txt
azure_graph_helper-1.0.1.2.dist-info/RECORD
