Metadata-Version: 2.1
Name: azure-graph-helper
Version: 1.0.1.2
Summary: Python library to manage Azure AD (Entra ID) user groups easily through Graph API.
Home-page: https://github.com/Ivanodib/azure-graph-helper
Author: Ivano Dibenedetto
Author-email: ivano.dibenedetto7@gmail.com
Classifier: License :: OSI Approved :: MIT License
Classifier: Programming Language :: Python :: 3
Classifier: Operating System :: OS Independent
License-File: LICENSE
